MANIFEST.in
README.md
setup.py
anthill/config/__init__.py
anthill/config/admin.py
anthill/config/handler.py
anthill/config/options.py
anthill/config/server.py
anthill/config/model/__init__.py
anthill/config/model/apps.py
anthill/config/model/builds.py
anthill/config/sql/config_application_versions.sql
anthill/config/sql/config_applications.sql
anthill/config/sql/config_builds.sql
anthill_config.egg-info/PKG-INFO
anthill_config.egg-info/SOURCES.txt
anthill_config.egg-info/dependency_links.txt
anthill_config.egg-info/namespace_packages.txt
anthill_config.egg-info/not-zip-safe
anthill_config.egg-info/requires.txt
anthill_config.egg-info/top_level.txt