Metadata-Version: 1.0
Name: anthill-config
Version: 0.2
Summary: Dynamic configuration service for Anthill platform
Home-page: https://github.com/anthill-platform/anthill-config
Author: desertkun
Author-email: desertkun@gmail.com
License: MIT
Platform: UNKNOWN
